text_replace/__init__.py
text_replace/__main__.py
text_replace/replace.py
text_replace/search_files.py
text_replace/presets/__init__.py
text_replace/presets/config.py
text_replace/presets/relative_url_prefixer.py
text_replace-0.1.2.dist-info/LICENSE
text_replace-0.1.2.dist-info/METADATA
text_replace-0.1.2.dist-info/WHEEL
text_replace-0.1.2.dist-info/top_level.txt
text_replace-0.1.2.dist-info/RECORD
