Metadata-Version: 2.1
Name: text-replace
Version: 0.1.2
Summary: A python package that traverse files based on some regex pattern to select certain files and then update the text in these files using regex.
Home-page: https://github.com/Salaah01/text-replace
Author: Salaah Amin
License: MIT
Platform: UNKNOWN
Classifier: Intended Audience :: Developers
Classifier: Operating System :: OS Independent
Classifier: Programming Language :: Python
Classifier: Programming Language :: Python :: 3
Classifier: Programming Language :: Python :: 3 :: Only
Classifier: Programming Language :: Python :: 3.6
Classifier: Programming Language :: Python :: 3.7
Classifier: Programming Language :: Python :: 3.8
Classifier: Programming Language :: Python :: 3.9
Classifier: Topic :: Software Development :: Libraries :: Python Modules
Requires-Python: >=3.6
